README.md
setup.cfg
setup.py
distributions/Binomialdistribution.py
distributions/Gaussiandistribution.py
distributions/Generaldistribution.py
distributions/__init__.py
distributionsAlyKhaled.egg-info/PKG-INFO
distributionsAlyKhaled.egg-info/SOURCES.txt
distributionsAlyKhaled.egg-info/dependency_links.txt
distributionsAlyKhaled.egg-info/not-zip-safe
distributionsAlyKhaled.egg-info/top_level.txt